{"cameraMode":{"drawMode":0,"name":"Shaded","section":"Shading Mode"},"sceneLighting":true,"audioPlay":false,"sceneViewState":{"m_AlwaysRefresh":false,"showFog":true,"showSkybox":true,"showFlares":true,"showImageEffects":true,"showParticleSystems":true,"showVisualEffectGraphs":true,"m_FxEnabled":true},"in2DMode":false,"pivot":{"x":6.170086860656738,"y":0.24578022956848145,"z":-3.075955629348755},"rotation":{"x":0.21552200615406037,"y":0.007202393840998411,"z":-0.0018550168024376035,"w":0.976596474647522},"size":1.7660253047943116,"orthographic":false}