{"cameraMode":{"drawMode":0,"name":"Shaded","section":"Shading Mode"},"sceneLighting":true,"audioPlay":false,"sceneViewState":{"m_AlwaysRefresh":false,"showFog":true,"showSkybox":true,"showFlares":true,"showImageEffects":true,"showParticleSystems":true,"showVisualEffectGraphs":true,"m_FxEnabled":true},"in2DMode":false,"pivot":{"x":-1.2539321184158326,"y":1.2172918319702149,"z":-2.3299989700317385},"rotation":{"x":-0.05517742410302162,"y":-0.2285645455121994,"z":0.012959458865225315,"w":-0.9719150066375732},"size":3.576817035675049,"orthographic":false}